corsaipy/__init__.py
corsaipy/corsai.py
corsaipy/sampler.py
corsaipy-0.1.1.dist-info/METADATA
corsaipy-0.1.1.dist-info/WHEEL
corsaipy-0.1.1.dist-info/top_level.txt
corsaipy-0.1.1.dist-info/RECORD
