Metadata-Version: 2.4
Name: corsaipy
Version: 0.1.1
Summary: A correlation-based sampling algorithm
Author-email: Stephan Balduin <stephan.balduin@offis.de>
Requires-Python: >=3.10
Requires-Dist: numpy
Provides-Extra: dev
Requires-Dist: black==22.3.0; extra == "dev"
Requires-Dist: wheel; extra == "dev"
Requires-Dist: flake8; extra == "dev"
